jamb/__init__.py
jamb/_version.py
jamb/py.typed
jamb/yaml_io.py
jamb/cli/__init__.py
jamb/cli/commands.py
jamb/config/__init__.py
jamb/config/loader.py
jamb/core/__init__.py
jamb/core/errors.py
jamb/core/models.py
jamb/coverage/__init__.py
jamb/coverage/serializer.py
jamb/matrix/__init__.py
jamb/matrix/chain_builder.py
jamb/matrix/generator.py
jamb/matrix/utils.py
jamb/matrix/formats/__init__.py
jamb/matrix/formats/csv.py
jamb/matrix/formats/html.py
jamb/matrix/formats/json.py
jamb/matrix/formats/markdown.py
jamb/matrix/formats/xlsx.py
jamb/publish/__init__.py
jamb/publish/formats/__init__.py
jamb/publish/formats/docx.py
jamb/publish/formats/html.py
jamb/pytest_plugin/__init__.py
jamb/pytest_plugin/collector.py
jamb/pytest_plugin/log.py
jamb/pytest_plugin/markers.py
jamb/pytest_plugin/plugin.py
jamb/storage/__init__.py
jamb/storage/discovery.py
jamb/storage/document_config.py
jamb/storage/document_dag.py
jamb/storage/graph_builder.py
jamb/storage/items.py
jamb/storage/reorder.py
jamb/storage/test_references.py
jamb/storage/validation.py
jamb-1.6.3.dist-info/METADATA
jamb-1.6.3.dist-info/WHEEL
jamb-1.6.3.dist-info/entry_points.txt
jamb-1.6.3.dist-info/licenses/LICENSE
jamb-1.6.3.dist-info/RECORD
