Metadata-Version: 2.4
Name: jamb
Version: 1.6.3
Summary: IEC 62304 requirements traceability for pytest
Author-email: Andrew Van <vanandrew77@gmail.com>
License: MIT License
License-File: LICENSE
Classifier: License :: OSI Approved :: MIT License
Classifier: Programming Language :: Python :: 3
Classifier: Programming Language :: Python :: 3.10
Classifier: Programming Language :: Python :: 3.11
Classifier: Programming Language :: Python :: 3.12
Classifier: Programming Language :: Python :: 3.13
Classifier: Programming Language :: Python :: 3.14
Requires-Python: >=3.10
Requires-Dist: click>=8.0
Requires-Dist: jinja2>=3.0
Requires-Dist: openpyxl>=3.0
Requires-Dist: pytest>=7.0
Requires-Dist: python-docx>=1.0
Requires-Dist: pyyaml>=6.0
Requires-Dist: tomli>=2.0; python_version < '3.11'
Requires-Dist: tomlkit>=0.12
